.gitignore
.travis.yml
LICENSE
MANIFEST.in
README.md
requirements.txt
setup.py
Orange3_Variants.egg-info/PKG-INFO
Orange3_Variants.egg-info/SOURCES.txt
Orange3_Variants.egg-info/dependency_links.txt
Orange3_Variants.egg-info/entry_points.txt
Orange3_Variants.egg-info/namespace_packages.txt
Orange3_Variants.egg-info/not-zip-safe
Orange3_Variants.egg-info/requires.txt
Orange3_Variants.egg-info/top_level.txt
doc/Makefile
doc/conf.py
doc/index.rst
doc/make.bat
doc/widgets/mywidget.md
doc/widgets/icons/mywidget.png
orangecontrib/__init__.py
orangecontrib/variants/__init__.py
orangecontrib/variants/exemplar.py
orangecontrib/variants/reader.py
orangecontrib/variants/tests/__init__.py
orangecontrib/variants/tests/test_example.py
orangecontrib/variants/tutorials/__init__.py
orangecontrib/variants/tutorials/example_tutorial.ows
orangecontrib/variants/widgets/__init__.py
orangecontrib/variants/widgets/owclusterstatistics.py
orangecontrib/variants/widgets/owexemplars.py
orangecontrib/variants/widgets/owvcf.py
orangecontrib/variants/widgets/icons/ClusterStatistics.svg
orangecontrib/variants/widgets/icons/VCFFile.svg
orangecontrib/variants/widgets/icons/category.svg