Metadata-Version: 1.1
Name: Orange3-Variants
Version: 0.0.3
Summary: Add-on for SNV calling from NGS data
Home-page: https://github.com/biolab/orange3-variants
Author: Bioinformatics Laboratory, FRI UL
Author-email: info@biolab.si
License: GPLv3+
Download-URL: https://github.com/biolab/orange3-variants/tarball/0.0.3
Keywords: orange3 add-on
Platform: UNKNOWN
